ispeak/__init__.py
ispeak/cli.py
ispeak/cli_commands.py
ispeak/cli_parse.py
ispeak/config.py
ispeak/console_helper.py
ispeak/core.py
ispeak/recorder.py
ispeak/plugin/__init__.py
ispeak/plugin/base.py
ispeak/plugin/loader.py
ispeak/plugin/builtin/__init__.py
ispeak/plugin/builtin/num2text.py
ispeak/plugin/builtin/replace.py
ispeak/plugin/builtin/text2num.py
ispeak-0.4.4.dist-info/METADATA
ispeak-0.4.4.dist-info/WHEEL
ispeak-0.4.4.dist-info/entry_points.txt
ispeak-0.4.4.dist-info/licenses/LICENSE
ispeak-0.4.4.dist-info/RECORD
