Metadata-Version: 2.4
Name: ispeak
Version: 0.4.4
Summary: An inline speech-to-text CLI tool that works wherever you can type
Project-URL: Homepage, https://github.com/fetchTe/ispeak
Project-URL: Documentation, https://github.com/fetchTe/ispeak#quick-start
Project-URL: Repository, https://github.com/fetchTe/ispeak.git
Project-URL: Issues, https://github.com/fetchTe/ispeak/issues
Project-URL: Changelog, https://github.com/fetchTe/ispeak/blob/master/CHANGELOG.md
Author-email: te <git@fetchte.com>
License-Expression: MIT
License-File: LICENSE
Keywords: aider,claude,cli,clipboard,codex,inline,keyboard,speech-to-text,stt,whisper
Requires-Python: >=3.11
Requires-Dist: pynput>=1.8.1
Requires-Dist: pyperclip>=1.9.0
Requires-Dist: realtimestt>=0.3.104
Provides-Extra: cpu
Requires-Dist: torch>=2.1.0; extra == 'cpu'
Requires-Dist: torchaudio>=2.1.0; extra == 'cpu'
Provides-Extra: cu118
Requires-Dist: torch>=2.1.0; extra == 'cu118'
Requires-Dist: torchaudio>=2.1.0; extra == 'cu118'
Provides-Extra: cu128
Requires-Dist: torch>=2.1.0; extra == 'cu128'
Requires-Dist: torchaudio>=2.1.0; extra == 'cu128'
Provides-Extra: plugin
Requires-Dist: num2words>=0.5.14; extra == 'plugin'
Requires-Dist: text2num>=3.0.0; extra == 'plugin'
